paymentsds/__init__.py
paymentsds/mpesa/__init__.py
paymentsds/mpesa/client.py
paymentsds/mpesa/configuration.py
paymentsds/mpesa/constants.py
paymentsds/mpesa/environment.py
paymentsds/mpesa/operation.py
paymentsds/mpesa/response.py
paymentsds/mpesa/service.py
paymentsds/mpesa/exceptions/__init__.py
paymentsds/mpesa/exceptions/authentication_error.py
paymentsds/mpesa/exceptions/invalid_host_error.py
paymentsds/mpesa/exceptions/invalid_receiver_error.py
paymentsds/mpesa/exceptions/missing_property_error.py
paymentsds/mpesa/exceptions/timeout_error.py
paymentsds/mpesa/exceptions/validation_error.py
paymentsds_mpesa-0.1a9.dist-info/LICENSE
paymentsds_mpesa-0.1a9.dist-info/METADATA
paymentsds_mpesa-0.1a9.dist-info/WHEEL
paymentsds_mpesa-0.1a9.dist-info/top_level.txt
paymentsds_mpesa-0.1a9.dist-info/RECORD
