Metadata-Version: 2.1
Name: paymentsds-mpesa
Version: 0.1a9
Summary: MPesa Python SDK
Home-page: https://github.com/paymentsds/mpesa-python-sdk
Author: Edson Michaque
Author-email: edson@michaque.com
License: Apache-2.0
Keywords: MPesa
Platform: UNKNOWN
Requires-Dist: requests (>=2.0.0)
Requires-Dist: pycryptodome
